jetset-1.3.0.dist-info/LICENSE.txt
jetset-1.3.0.dist-info/zip-safe
jetset-1.3.0.dist-info/WHEEL
jetset-1.3.0.dist-info/top_level.txt
jetset-1.3.0.dist-info/RECORD
jetset-1.3.0.dist-info/METADATA
jetset/mcmc.py
jetset/jetkernel_models_dic.py
jetset/sed_shaper.py
jetset/test_data_helper.py
jetset/cosmo_tools.py
jetset/jet_emitters_factory.py
jetset/jet_kernel_tools.py
jetset/jet_tools.py
jetset/template_2Dmodel.py
jetset/jet_timedep.py
jetset/frame_converter.py
jetset/model_parameters.py
jetset/loglog_poly_model.py
jetset/pkg_info.json
jetset/model_manager.py
jetset/jet_spectral_components.py
jetset/version_notifier.py
jetset/plot_sedfit.py
jetset/mock.py
jetset/poly_fit_tools.py
jetset/poly_fit.py
jetset/template_model.py
jetset/utils.py
jetset/output.py
jetset/jet_emitters.py
jetset/jet_model.py
jetset/minimizer.py
jetset/base_model.py
jetset/sherpa_plugin.py
jetset/obs_constrain.py
jetset/spectral_shapes.py
jetset/convert_qdp.py
jetset/jet_paramters.py
jetset/mathkernel_helper.py
jetset/analytical_model.py
jetset/__init__.py
jetset/data_loader.py
jetset/gammapy_plugin.py
jetset/jetkernel/_jetkernel.cpython-310-x86_64-linux-gnu.so
jetset/jetkernel/jetkernel.i
jetset/jetkernel/__init__.py
jetset/jetkernel/jetkernel.py
jetset/jetkernel/mathkernel/template_F_Sync.dat
jetset/jetkernel/mathkernel/F_Sync.dat
jetset/mathkernel/template_F_Sync.dat
jetset/mathkernel/F_Sync.dat
jetset/tests/test_depending_parameters.py
jetset/tests/test_data.py
jetset/tests/base_class.py
jetset/tests/test_mcmc.py
jetset/tests/test_ebl.py
jetset/tests/test_galactic.py
jetset/tests/test_integration.py
jetset/tests/test_phenom_constr.py
jetset/tests/test_temp_ev.py
jetset/tests/test_composite_model.py
jetset/tests/test_model_fit.py
jetset/tests/test_emitters.py
jetset/tests/test_hadronic_energetic.py
jetset/tests/test_users.py
jetset/tests/__init__.py
jetset/tests/test_jet_model.py
jetset/Spectral_Templates_Repo/QSO_BBB_Template.dat
jetset/Spectral_Templates_Repo/HostgalaxyTemplate.dat
jetset/Spectral_Templates_Repo/HostgalaxyTemplate_Orig.dat
jetset/Spectral_Templates_Repo/QSO_BBB_Template_Orig.dat
