Metadata-Version: 2.1
Name: jetset
Version: 1.3.0
Summary: A framework for self-consistent modeling and fitting of  astrophysical relativistic jets SEDs
Home-page: https://github.com/andreatramacere/jetset
Author: Andrea Tramacere
Author-email: andrea.tramacere@gmail.com
Requires-Python: >=3.8
License-File: LICENSE.txt
Requires-Dist: setuptools
Requires-Dist: scipy (<=1.13.1,>=1.5.0)
Requires-Dist: numpy (<2.0,>=1.22)
Requires-Dist: astropy (<=6,>=5.0.1)
Requires-Dist: matplotlib (>=3.1.0)
Requires-Dist: future
Requires-Dist: iminuit (<=2.17.0,>=2.0.0)
Requires-Dist: corner
Requires-Dist: six
Requires-Dist: emcee (<=3.1.6,>=3.0.0)
Requires-Dist: pyyaml
Requires-Dist: pytest
Requires-Dist: numba (<=0.59.1,>0.55)
Requires-Dist: tqdm (<5)
Requires-Dist: jupyter
Requires-Dist: ipython
Requires-Dist: dill
Requires-Dist: swig (>=4)
